<?xml version="1.0" encoding="utf-8" ?>
<dwsync>
<file name="pro_drag_frame2_f1.html" server="//192.168.10.4/dvmsys/" local="130486946950000000" remote="130486946950000000" />
<file name="pro_drag_frame2_f2.html" server="//192.168.10.4/dvmsys/" local="130486946950000000" remote="130486946950000000" />
<file name="pro_drag_frame2_f3.html" server="//192.168.10.4/dvmsys/" local="130486946950000000" remote="130486946950000000" />
<file name="pro_drag_frame_f1.html" server="//192.168.10.4/dvmsys/" local="130486946950000000" remote="130486946950000000" />
<file name="pro_drag_frame_f2.html" server="//192.168.10.4/dvmsys/" local="130486946950000000" remote="130486946950000000" />
<file name="pro_drag_frame_f3.html" server="//192.168.10.4/dvmsys/" local="130486946950000000" remote="130486946950000000" />
<file name="pro_drag_frame2_f1.html" server="//Dvmzab/dvmzab/opt/lampp/htdocs/dvmsys/" local="130486946950000000" remote="130486946950000000" />
<file name="pro_drag_frame2_f2.html" server="//Dvmzab/dvmzab/opt/lampp/htdocs/dvmsys/" local="130486946950000000" remote="130486946950000000" />
<file name="pro_drag_frame2_f3.html" server="//Dvmzab/dvmzab/opt/lampp/htdocs/dvmsys/" local="130486946950000000" remote="130486946950000000" />
<file name="pro_drag_frame_f1.html" server="//Dvmzab/dvmzab/opt/lampp/htdocs/dvmsys/" local="130486946950000000" remote="130486946950000000" />
<file name="pro_drag_frame_f2.html" server="//Dvmzab/dvmzab/opt/lampp/htdocs/dvmsys/" local="130486946950000000" remote="130486946950000000" />
<file name="pro_drag_frame_f3.html" server="//Dvmzab/dvmzab/opt/lampp/htdocs/dvmsys/" local="130486946950000000" remote="130486946950000000" />
</dwsync>